normalai/__init__.py
normalai-0.0.0.dist-info/METADATA
normalai-0.0.0.dist-info/WHEEL
normalai-0.0.0.dist-info/top_level.txt
normalai-0.0.0.dist-info/RECORD
